pdftools/__init__.py
pdftools/pdftools.py
translationPdF-2.0.0.dist-info/LICENCE
translationPdF-2.0.0.dist-info/METADATA
translationPdF-2.0.0.dist-info/WHEEL
translationPdF-2.0.0.dist-info/top_level.txt
translationPdF-2.0.0.dist-info/RECORD
