Metadata-Version: 2.1
Name: translationPdF
Version: 2.0.0
Summary: translationPdF é um pacote para a tradução de PDF.
Home-page: https://github.com/Willians-S-S/PacoteTranslation
Author: Willians Silva
Author-email: 09willians@gmail.com
Classifier: Programming Language :: Python :: 3
Classifier: License :: OSI Approved :: MIT License
Classifier: Operating System :: OS Independent
Requires-Python: >=3.5
License-File: LICENCE
Requires-Dist: pypdf2
Requires-Dist: fpdf2
Requires-Dist: pytesseract
Requires-Dist: googletrans (==4.0.0-rc1)
